pchain/__init__.py
pchain/__main__.py
pchain/debug.py
pchain/loader.py
pchain/pack.py
pchain/pydata.py
pchain/pyproc.py
pchain/runner.py
pchain/darwin/libstar_pchain.dylib
pchain/darwin/libstar_python34.so
pchain/darwin/libstar_python35.so
pchain/darwin/libstar_python36.so
pchain/darwin/libstar_python37.so
pchain/darwin/libstarcore.dylib
pchain/darwin/libstarpy.so
pchain/linux/libstar_pchain.so
pchain/linux/libstar_python34.so
pchain/linux/libstar_python35.so
pchain/linux/libstar_python36.so
pchain/linux/libstar_python37.so
pchain/linux/libstarcore.so
pchain/linux/libstarpy.so
pchain/linux/ubuntu/libstar_pchain.so
pchain/linux/ubuntu/libstar_python34.so
pchain/linux/ubuntu/libstar_python35.so
pchain/linux/ubuntu/libstar_python36.so
pchain/linux/ubuntu/libstar_python37.so
pchain/linux/ubuntu/libstarcore.so
pchain/linux/ubuntu/libstarpy.so
pchain/template/package_main.py
pchain/template/package_rawmain.py
pchain/template/packageinfo.json
pchain/template/project_main.py
pchain/template/project_rawmain.py
pchain/tools/__init__.py
pchain/tools/pcmanager.py
pchain/tools/pcpack.py
pchain/tools/pcpackinstall.py
pchain/tools/pcrunner.py
pchain/webpage/app.js
pchain/webpage/d3.v3.min.js
pchain/webpage/d3.v5.min.js
pchain/webpage/index.html
pchain/windows/32/libstar_python34.pyd
pchain/windows/32/libstar_python35.pyd
pchain/windows/32/libstar_python36.pyd
pchain/windows/32/libstar_python37.pyd
pchain/windows/32/libstarcore.dll
pchain/windows/32/libstarpy.pyd
pchain/windows/32/star_pchain.dll
pchain/windows/64/libstar_python34.pyd
pchain/windows/64/libstar_python35.pyd
pchain/windows/64/libstar_python36.pyd
pchain/windows/64/libstar_python37.pyd
pchain/windows/64/libstarcore.dll
pchain/windows/64/libstarpy.pyd
pchain/windows/64/star_pchain.dll
pchain-0.5.0.dist-info/METADATA
pchain-0.5.0.dist-info/WHEEL
pchain-0.5.0.dist-info/top_level.txt
pchain-0.5.0.dist-info/RECORD
