Metadata-Version: 2.1
Name: pchain
Version: 0.5.0
Summary: Foundation of flexible, shareable and creative data-driven programming technology
Home-page: https://github.com/srplab/pchain
Author: srplab
Author-email: srplab.cn@hotmail.com
License: MIT Licence
Keywords: process chain
Platform: any
Requires-Dist: requests
